[
  {
    "id": "5f5a38d3dee57",
    "firstname": "Nikul\u00e1s",
    "lastname": "\u00d3skarsson",
    "username": "nikulasoskarsson",
    "email": "nikulasoskarsson@gmail.com",
    "password": "$2y$10$88MOey0xoiW2EpTxyveRF.QnQkhNaApsAXp/djCqDmwysdzx1O1Wi",
    "dob": { "month": "1", "year": "1900", "day": "14" }
  },
  {
    "id": "5f5cdfeb29a20",
    "firstname": "Nikul\u00e1s",
    "lastname": "\u00d3skarsson",
    "username": "testuser",
    "email": "test@test.com",
    "password": "$2y$10$UJc9d41dwO9IhNvbpK0keuTrjPKrQqCgbwuZ1fSGE4NBFdb7VwcDq",
    "dob": { "month": "9", "year": "1913", "day": "13" }
  },
  {
    "id": "5f6343940ac47",
    "firstname": "Dan\u00edel",
    "lastname": "\u00d3skarsson",
    "username": "danieloskarsson",
    "email": "danieloskarsson@gmail.com",
    "password": "$2y$10$rrR5GqEcRXqaJtbTzmAE7ObQjcnhtwxuzLsKNXWA.MfCWvYgefhuy",
    "dob": { "month": "12", "year": "1915", "day": "12" }
  }
]
